tap_snowflake/__init__.py
tap_snowflake/client.py
tap_snowflake/tap.py
meltanolabs_tap_snowflake-0.2.0.dist-info/METADATA
meltanolabs_tap_snowflake-0.2.0.dist-info/WHEEL
meltanolabs_tap_snowflake-0.2.0.dist-info/entry_points.txt
meltanolabs_tap_snowflake-0.2.0.dist-info/licenses/LICENSE
meltanolabs_tap_snowflake-0.2.0.dist-info/RECORD
