Metadata-Version: 2.4
Name: meltanolabs-tap-snowflake
Version: 0.2.0
Summary: `tap-snowflake` is a Singer tap for Snowflake, built with the Meltano SDK for Singer Taps.
License: Apache-2.0
License-File: LICENSE
Keywords: ELT,Meltano,Snowflake
Author: Meltano Team
Author-email: hello@meltano.com
Requires-Python: >=3.10,<4
Classifier: License :: OSI Approved :: Apache Software License
Classifier: Programming Language :: Python :: 3
Classifier: Programming Language :: Python :: 3.10
Classifier: Programming Language :: Python :: 3.11
Classifier: Programming Language :: Python :: 3.12
Classifier: Programming Language :: Python :: 3.13
Classifier: Programming Language :: Python :: 3.14
Requires-Dist: cryptography (>=40)
Requires-Dist: singer-sdk (>=0.49.1,<0.50.0)
Requires-Dist: snowflake-connector-python[secure-local-storage] (>=3.17.4,<3.18.0)
Requires-Dist: snowflake-sqlalchemy (==1.7.7)
Requires-Dist: sqlalchemy (>=2.0.43,<2.1.0)
